platon_keys/__init__.py
platon_keys/constants.py
platon_keys/datatypes.py
platon_keys/exceptions.py
platon_keys/main.py
platon_keys/validation.py
platon_keys/backends/__init__.py
platon_keys/backends/base.py
platon_keys/backends/coincurve.py
platon_keys/backends/native/__init__.py
platon_keys/backends/native/ecdsa.py
platon_keys/backends/native/jacobian.py
platon_keys/backends/native/main.py
platon_keys/tools/__init__.py
platon_keys/tools/factories.py
platon_keys/utils/__init__.py
platon_keys/utils/address.py
platon_keys/utils/der.py
platon_keys/utils/module_loading.py
platon_keys/utils/numeric.py
platon_keys/utils/padding.py
platon_keys-1.2.0.dist-info/LICENSE
platon_keys-1.2.0.dist-info/METADATA
platon_keys-1.2.0.dist-info/WHEEL
platon_keys-1.2.0.dist-info/top_level.txt
platon_keys-1.2.0.dist-info/RECORD
